{
  "__metadata": {
    "id": "https://api.sap.com/odata/1.0/catalog.svc/APIContent.APIs('sapdme_integrationMessage')",
    "uri": "https://api.sap.com/odata/1.0/catalog.svc/APIContent.APIs('sapdme_integrationMessage')",
    "type": "APIContent.API",
    "content_type": "application/octet-stream",
    "media_src": "https://api.sap.com/odata/1.0/catalog.svc/APIContent.APIs('sapdme_integrationMessage')/$value",
    "edit_media": "https://api.sap.com/odata/1.0/catalog.svc/APIContent.APIs('sapdme_integrationMessage')/$value"
  },
  "Name": "sapdme_integrationMessage",
  "ID": "sapdme_integrationMessage",
  "Title": "Integration Messages",
  "ShortText": "Interact with integration messages in the Manage Integration Dashboard.",
  "Description": null,
  "Direction": null,
  "Version": "v1",
  "ServiceCode": "REST",
  "ServiceUrl": null,
  "Deprecated": null,
  "hasManagedContent": false,
  "CreatedAt": "/Date(1708922732333)/",
  "CreatedBy": "XXX",
  "ModifiedAt": "/Date(1770994706785)/",
  "ModifiedBy": "XXX",
  "ParentTechnicalName": "SAPDigitalManufacturingCloud",
  "State": "ACTIVE",
  "ChangeLog": "[{\"date\":\"24 Feb 2024\",\"notes\":\"Added new API for getting integration message list and for setting integration messages displayed in the Integration Message Dashboard to inactive.\",\"state\":\"Active\",\"version\":\"v1\"}]",
  "ExternalDocs": null,
  "ReleaseInfo": null,
  "MultiVersion": false,
  "BusinessObjects": null,
  "Successors": null,
  "OrdId": null,
  "Versions": {
    "__deferred": {
      "uri": "https://api.sap.com/odata/1.0/catalog.svc/APIContent.APIs('sapdme_integrationMessage')/Versions"
    }
  }
}